SiEPIC/__init__.py
SiEPIC/_globals.py
SiEPIC/calibre_temp.py
SiEPIC/core.py
SiEPIC/example_gr.py
SiEPIC/examples.py
SiEPIC/extend.py
SiEPIC/github.py
SiEPIC/install.py
SiEPIC/metal_menu_helper.py
SiEPIC/netlist.py
SiEPIC/opics_netlist_sim.py
SiEPIC/scripts.py
SiEPIC/setup.py
SiEPIC/verification.py
SiEPIC/lumerical/ApodizedContraDC.py
SiEPIC/lumerical/__init__.py
SiEPIC/lumerical/contraDirectionalCoupler.py
SiEPIC/lumerical/fdtd.py
SiEPIC/lumerical/interconnect.py
SiEPIC/lumerical/load_lumapi.py
SiEPIC/lumerical/mode.py
SiEPIC/opics/__init__.py
SiEPIC/opics/components.py
SiEPIC/opics/globals.py
SiEPIC/opics/network.py
SiEPIC/opics/sparam_ops.py
SiEPIC/opics/utils.py
SiEPIC/opics/libraries/__init__.py
SiEPIC/opics/libraries/catalogue.yaml
SiEPIC/opics/libraries/catalogue_mgmt.py
SiEPIC/simulation/__init__.py
SiEPIC/simulation/contraDC/__init__.py
SiEPIC/simulation/contraDC/contraDC_klayout_gui.py
SiEPIC/simulation/contraDC/klayout_gui.py
SiEPIC/simulation/contraDC/Tutorial/examples.py
SiEPIC/simulation/contraDC/contra_directional_coupler/ContraDC.py
SiEPIC/simulation/contraDC/contra_directional_coupler/__init__.py
SiEPIC/simulation/contraDC/contra_directional_coupler/lumerical_tools.py
SiEPIC/simulation/contraDC/contra_directional_coupler/modules.py
SiEPIC/simulation/contraDC/contra_directional_coupler/utils.py
SiEPIC/tests/test_box_bezier_corners.py
SiEPIC/tests/test_dft_aim_verification.py
SiEPIC/tests/test_path_radius_check.py
SiEPIC/tests/test_port.py
SiEPIC/tests/test_scripts_layout_diff.py
SiEPIC/tests/test_replace_cell/test_scripts_replace_cell.py
SiEPIC/tidy3d/lint.py
SiEPIC/tidy3d/make_script.py
SiEPIC/tidy3d/schema.py
SiEPIC/tidy3d/setup.py
SiEPIC/tidy3d/tests/__init__.py
SiEPIC/tidy3d/tests/utils.py
SiEPIC/tidy3d/tests/_test_local/__init__.py
SiEPIC/tidy3d/tests/_test_local/_test_adjoint_performance.py
SiEPIC/tidy3d/tests/_test_local/_test_data_performance.py
SiEPIC/tidy3d/tests/_test_local/_test_fit_web.py
siepic-0.5.31.dist-info/METADATA
siepic-0.5.31.dist-info/WHEEL
siepic-0.5.31.dist-info/top_level.txt
siepic-0.5.31.dist-info/RECORD
