Metadata-Version: 2.4
Name: SiEPIC
Version: 0.5.31
Summary: SiEPIC-Tools: for silicon photonics layout, design, verification and circuit simulation
Author-email: Lukas Chrostowski <lukasc@ece.ubc.ca>
Project-URL: Homepage, https://github.com/SiEPIC/SiEPIC-Tools
Project-URL: Issues, https://github.com/SiEPIC/SiEPIC-Tools/issues
Classifier: Programming Language :: Python :: 3
Classifier: License :: OSI Approved :: MIT License
Classifier: Operating System :: OS Independent
Requires-Python: >=3.8
Requires-Dist: numpy
Requires-Dist: scipy
Requires-Dist: pandas
Requires-Dist: requests
Requires-Dist: IPython
Requires-Dist: klayout
